LICENSE
MANIFEST.in
README.md
setup.cfg
setup.py
erscimenu/__init__.py
erscimenu/admin.py
erscimenu/apps.py
erscimenu/menu.py
erscimenu/models.py
erscimenu/tests.py
erscimenu/views.py
erscimenu.egg-info/PKG-INFO
erscimenu.egg-info/SOURCES.txt
erscimenu.egg-info/dependency_links.txt
erscimenu.egg-info/top_level.txt
erscimenu/migrations/0001_initial.py
erscimenu/migrations/__init__.py
erscimenu/migrations/__pycache__/0001_initial.cpython-310.pyc
erscimenu/migrations/__pycache__/__init__.cpython-310.pyc