Metadata-Version: 2.1
Name: erscimenu
Version: 1.0.7
Summary: Create UL LI html menu from django model queryset.
Home-page: https://github.com/epg900/erscimenu.git
Author: epg
Author-email: epg900@gmail.com
License: GNU GENERAL PUBLIC LICENSE
Platform: UNKNOWN
Requires-Python: >=3.7
License-File: LICENSE
